main.py
echoshell/__init__.py
echoshell/agent_protocol.py
echoshell/capability_registry.py
echoshell/cli.py
echoshell/edgehub_client.py
echoshell/init_agents.py
echoshell/neural_bridge.py
echoshell/redis_connector.py
echoshell/scene_sprouter.py
echoshell/vault_whisper.py
echoshell/web_ui.py
echoshell/.aureon/cli_extensions/thread_opener.py
echoshell/aureon/cli_extensions/git_pr_binder.py
echoshell/github/projects_api.py
echothreads/__init__.py
echothreads/semiotic_table.py
loreweave/__init__.py
loreweave/openapi_specweaver.py
loreweave/parser.py
loreweave/visualize_intentions.py
loreweave/visualize_narratives.py
scripts/__init__.py
scripts/chroma_fonction.py
scripts/loreweave_runner.py
scripts/mia_status.py
scripts/proto_llm_simple_250430.py
scripts/revise_plan.py
scripts/seed_reflection.py
scripts/whisper_route.py
echothreads-0.3.3.dist-info/LICENSE
echothreads-0.3.3.dist-info/METADATA
echothreads-0.3.3.dist-info/WHEEL
echothreads-0.3.3.dist-info/entry_points.txt
echothreads-0.3.3.dist-info/top_level.txt
echothreads-0.3.3.dist-info/RECORD
