Metadata-Version: 2.2
Name: echothreads
Version: 0.3.3
Summary: A system that transforms code changes into narratives, capturing the essence and intention of each commit.
Home-page: https://github.com/jgwill/EchoThreads
Author: Your Name
Author-email: your.email@example.com
Classifier: Programming Language :: Python :: 3
Classifier: License :: OSI Approved :: MIT License
Classifier: Operating System :: OS Independent
Requires-Python: >=3.10
License-File: LICENSE
Requires-Dist: redis
Requires-Dist: pyyaml
Requires-Dist: matplotlib
Requires-Dist: requests
Requires-Dist: click
Dynamic: author
Dynamic: author-email
Dynamic: classifier
Dynamic: description
Dynamic: description-content-type
Dynamic: home-page
Dynamic: requires-dist
Dynamic: requires-python
Dynamic: summary
